nestedpacket/__init__.py
nestedpacket/ethernet.py
nestedpacket/nestedpacket.py
nestedpacket/tcpip.py
nestedpacket/textboxprinter.py
nestedpacket/udpdatagram.py
nestedpacket-0.0.3.dist-info/LICENSE
nestedpacket-0.0.3.dist-info/WHEEL
nestedpacket-0.0.3.dist-info/METADATA
nestedpacket-0.0.3.dist-info/RECORD
