Metadata-Version: 2.1
Name: nestedpacket
Version: 0.0.3
Summary: A framework for generating, unpacking/dissecting and displaying layered packets
Author-email: Ashley Winn <ashley.winn@gmail.com>
Classifier: License :: OSI Approved :: MIT License
Requires-Dist: bitstring >=4.0.1
Requires-Dist: pytest >=7.2.0 ; extra == "test"
Project-URL: Source, https://github.com/ashleywinn/nestedpacket
Provides-Extra: test
